{
    "states": {
        "alabama": "America/Chicago",
        "alaska": "America/Anchorage",
        "arizona": "America/Phoenix",
        "arkansas": "America/Chicago",
        "california": "America/Los_Angeles",
        "colorado": "America/Denver",
        "connecticut": "America/New_York",
        "delaware": "America/New_York",
        "florida": "America/New_York",
        "georgia": "America/New_York",
        "hawaii": "Pacific/Honolulu",
        "idaho": "America/Boise",
        "illinois": "America/Chicago",
        "indiana": "America/Indiana/Indianapolis",
        "iowa": "America/Chicago",
        "kansas": "America/Chicago",
        "kentucky": "America/New_York",
        "louisiana": "America/Chicago",
        "maine": "America/New_York",
        "maryland": "America/New_York",
        "massachusetts": "America/New_York",
        "michigan": "America/Detroit",
        "minnesota": "America/Chicago",
        "mississippi": "America/Chicago",
        "missouri": "America/Chicago",
        "montana": "America/Denver",
        "nebraska": "America/Chicago",
        "nevada": "America/Los_Angeles",
        "new hampshire": "America/New_York",
        "new jersey": "America/New_York",
        "new mexico": "America/Denver",
        "new york": "America/New_York",
        "north carolina": "America/New_York",
        "north dakota": "America/Chicago",
        "ohio": "America/New_York",
        "oklahoma": "America/Chicago",
        "oregon": "America/Los_Angeles",
        "pennsylvania": "America/New_York",
        "rhode island": "America/New_York",
        "south carolina": "America/New_York",
        "south dakota": "America/Chicago",
        "tennessee": "America/Chicago",
        "texas": "America/Chicago",
        "utah": "America/Denver",
        "vermont": "America/New_York",
        "virginia": "America/New_York",
        "washington": "America/Los_Angeles",
        "west virginia": "America/New_York",
        "wisconsin": "America/Chicago",
        "wyoming": "America/Denver"
    },
    "cities": {
        "new york": "America/New_York",
        "los angeles": "America/Los_Angeles",
        "chicago": "America/Chicago",
        "houston": "America/Chicago",
        "phoenix": "America/Phoenix",
        "philadelphia": "America/New_York",
        "san antonio": "America/Chicago",
        "san diego": "America/Los_Angeles",
        "dallas": "America/Chicago",
        "san jose": "America/Los_Angeles",
        "austin": "America/Chicago",
        "jacksonville": "America/New_York",
        "fort worth": "America/Chicago",
        "columbus": "America/New_York",
        "san francisco": "America/Los_Angeles",
        "charlotte": "America/New_York",
        "indianapolis": "America/Indiana/Indianapolis",
        "seattle": "America/Los_Angeles",
        "denver": "America/Denver",
        "washington dc": "America/New_York",
        "boston": "America/New_York",
        "el paso": "America/Denver",
        "detroit": "America/Detroit",
        "nashville": "America/Chicago",
        "portland": "America/Los_Angeles",
        "memphis": "America/Chicago",
        "oklahoma city": "America/Chicago",
        "las vegas": "America/Los_Angeles",
        "louisville": "America/Kentucky/Louisville",
        "baltimore": "America/New_York",
        "milwaukee": "America/Chicago",
        "albuquerque": "America/Denver",
        "tucson": "America/Phoenix",
        "fresno": "America/Los_Angeles",
        "sacramento": "America/Los_Angeles",
        "kansas city": "America/Chicago",
        "miami": "America/New_York",
        "atlanta": "America/New_York",
        "new orleans": "America/Chicago",
        "cincinnati": "America/New_York",
        "salt lake city": "America/Denver",
        "pittsburgh": "America/New_York",
        "orlando": "America/New_York",
        "cleveland": "America/New_York",
        "buffalo": "America/New_York",
        "minneapolis": "America/Chicago",
        "st louis": "America/Chicago",
        "tampa": "America/New_York",
        "honolulu": "Pacific/Honolulu",
        "anchorage": "America/Anchorage"
    }
} 